rrtplanner/__init__.py
rrtplanner/anim.py
rrtplanner/oggen.py
rrtplanner/plots.py
rrtplanner/rrt.py
rrtplanner-0.1.2.dist-info/LICENSE
rrtplanner-0.1.2.dist-info/METADATA
rrtplanner-0.1.2.dist-info/WHEEL
rrtplanner-0.1.2.dist-info/top_level.txt
rrtplanner-0.1.2.dist-info/RECORD
