Metadata-Version: 2.1
Name: rrtplanner
Version: 0.1.2
Summary: Vectorized RRT, RRT*, and RRT*Informed planning in Python!
Home-page: https://github.com/rland93/rrtplanner
Author: Mike Sutherland
Author-email: msutherl@uci.edu
License: UNKNOWN
Project-URL: Bug Reports, https://github.com/rland93/rrtplanner/issues
Project-URL: Source, https://github.com/rland93/rrtplanner
Keywords: robotics,path planning
Platform: UNKNOWN
Classifier: Development Status :: 3 - Alpha
Classifier: Intended Audience :: Developers
Classifier: Topic :: Software Development :: Build Tools
Classifier: License :: OSI Approved :: MIT License
Classifier: Programming Language :: Python :: 3.7
Classifier: Programming Language :: Python :: 3 :: Only
Requires-Python: >=3.6, <4
Requires-Dist: numpy (>=1.18)
Requires-Dist: matplotlib (>=3.4)
Requires-Dist: networkx (>=2.6)
Requires-Dist: scipy (>=1.7)
Requires-Dist: tqdm (>=4)
Requires-Dist: numba (>=0.50)
Requires-Dist: pyfastnoisesimd (>=0.4)
